src/__init__.py
src/main.py
convertcurrency-0.0.4.dist-info/LICENSE.txt
convertcurrency-0.0.4.dist-info/METADATA
convertcurrency-0.0.4.dist-info/WHEEL
convertcurrency-0.0.4.dist-info/top_level.txt
convertcurrency-0.0.4.dist-info/RECORD
