Metadata-Version: 2.1
Name: convertcurrency
Version: 0.0.4
Summary: A basic currency converter
Home-page: 
Author: Rihand Parde
Author-email: rihand.parde@gmail.com
License: MIT
Keywords: currency converter
Classifier: Development Status :: 5 - Production/Stable
Classifier: Intended Audience :: Education
Classifier: Operating System :: Microsoft :: Windows :: Windows 10
Classifier: License :: OSI Approved :: MIT License
Classifier: Programming Language :: Python :: 3
License-File: LICENSE.txt
